README
flask_mustache.py
setup.py
Flask_Mustache.egg-info/PKG-INFO
Flask_Mustache.egg-info/SOURCES.txt
Flask_Mustache.egg-info/dependency_links.txt
Flask_Mustache.egg-info/not-zip-safe
Flask_Mustache.egg-info/requires.txt
Flask_Mustache.egg-info/top_level.txt