Metadata-Version: 1.1
Name: Flask-Mustache
Version: 0.4.1
Summary: Mustache for Flask
Home-page: http://github.com/ahri/flask-mustache
Author: Adam Piper
Author-email: adam@ahri.net
License: MIT
Platform: any
Classifier: Development Status :: 4 - Beta
Classifier: Environment :: Web Environment
Classifier: Intended Audience :: Developers
Classifier: License :: OSI Approved :: MIT License
Classifier: Operating System :: OS Independent
Classifier: Programming Language :: Python
Classifier: Topic :: Internet :: WWW/HTTP :: Dynamic Content
Classifier: Topic :: Software Development :: Libraries :: Python Modules
